README.md
rrn.py
setup.py
RRN.egg-info/PKG-INFO
RRN.egg-info/SOURCES.txt
RRN.egg-info/dependency_links.txt
RRN.egg-info/top_level.txt