Metadata-Version: 1.2
Name: RRN
Version: 0.2.0
Summary: Python library for dealing with Resident Registration Number of Korea
Home-page: https://github.com/Rainist/rrn
Author: Sunghyun Hwang
Author-email: me@sunghyunzz.com
Maintainer: Rainist
Maintainer-email: engineering@rainist.com
License: UNKNOWN
Platform: UNKNOWN
Classifier: Development Status :: 3 - Alpha
Classifier: Operating System :: OS Independent
Classifier: License :: OSI Approved :: MIT License
Classifier: Programming Language :: Python :: 3.5
Classifier: Programming Language :: Python :: 3.6
Classifier: Programming Language :: Python :: 3.7
Requires-Python: >=3.5
